{
  "49b4f59afc74417d846ad8cf1634e3d8": {
    "922": {
      "name": "box",
      "visible_pos": [
        0,
        10,
        11,
        12,
        22,
        23
      ],
      "bbox2d": [
        [
          0,
          218,
          36,
          24
        ],
        [
          418,
          177,
          61,
          32
        ],
        [
          216,
          174,
          53,
          36
        ],
        [
          0,
          452,
          1,
          3
        ],
        [
          429,
          402,
          64,
          39
        ],
        [
          206,
          400,
          59,
          41
        ]
      ]
    },
    "925": {
      "name": "plant",
      "visible_pos": [
        0,
        1,
        10,
        11,
        12,
        13,
        22,
        23
      ],
      "bbox2d": [
        [
          14,
          55,
          254,
          164
        ],
        [
          0,
          157,
          22,
          71
        ],
        [
          470,
          58,
          170,
          192
        ],
        [
          259,
          49,
          230,
          159
        ],
        [
          0,
          284,
          267,
          168
        ],
        [
          0,
          396,
          4,
          9
        ],
        [
          481,
          286,
          159,
          147
        ],
        [
          256,
          279,
          239,
          161
        ]
      ]
    },
    "929": {
      "name": "countertop",
      "visible_pos": [
        0,
        1,
        2,
        3,
        9,
        10,
        11,
        12,
        13,
        14,
        22,
        23
      ],
      "bbox2d": [
        [
          0,
          112,
          640,
          218
        ],
        [
          0,
          139,
          466,
          267
        ],
        [
          0,
          149,
          268,
          268
        ],
        [
          0,
          220,
          53,
          111
        ],
        [
          606,
          265,
          34,
          60
        ],
        [
          385,
          160,
          255,
          255
        ],
        [
          189,
          111,
          451,
          298
        ],
        [
          0,
          336,
          640,
          144
        ],
        [
          0,
          362,
          480,
          118
        ],
        [
          94,
          373,
          166,
          107
        ],
        [
          394,
          384,
          246,
          96
        ],
        [
          170,
          334,
          470,
          146
        ]
      ]
    },
    "931": {
      "name": "window",
      "visible_pos": [
        0,
        1,
        11,
        12,
        13,
        23,
        24,
        25,
        34,
        35
      ],
      "bbox2d": [
        [
          147,
          0,
          211,
          75
        ],
        [
          0,
          0,
          105,
          87
        ],
        [
          399,
          0,
          241,
          84
        ],
        [
          167,
          0,
          191,
          301
        ],
        [
          0,
          0,
          128,
          311
        ],
        [
          392,
          0,
          221,
          309
        ],
        [
          149,
          184,
          209,
          296
        ],
        [
          0,
          113,
          167,
          367
        ],
        [
          593,
          107,
          47,
          163
        ],
        [
          383,
          149,
          257,
          331
        ]
      ]
    },
    "932": {
      "name": "window#frame",
      "visible_pos": [
        0,
        1,
        11,
        12,
        13,
        23,
        24,
        25,
        34,
        35
      ],
      "bbox2d": [
        [
          144,
          51,
          197,
          15
        ],
        [
          86,
          68,
          1,
          1
        ],
        [
          390,
          48,
          23,
          15
        ],
        [
          159,
          15,
          195,
          278
        ],
        [
          102,
          0,
          19,
          296
        ],
        [
          384,
          46,
          221,
          253
        ],
        [
          157,
          184,
          194,
          282
        ],
        [
          29,
          124,
          136,
          210
        ],
        [
          596,
          104,
          44,
          201
        ],
        [
          383,
          154,
          210,
          312
        ]
      ]
    },
    "935": {
      "name": "toiletry",
      "visible_pos": [
        0,
        1,
        2,
        11,
        12,
        13,
        14
      ],
      "bbox2d": [
        [
          378,
          94,
          233,
          161
        ],
        [
          161,
          91,
          203,
          129
        ],
        [
          0,
          111,
          152,
          150
        ],
        [
          622,
          165,
          18,
          91
        ],
        [
          381,
          318,
          243,
          162
        ],
        [
          154,
          315,
          211,
          139
        ],
        [
          0,
          334,
          136,
          146
        ]
      ]
    },
    "937": {
      "name": "bath#cabinet",
      "visible_pos": [
        0,
        1,
        2,
        3,
        9,
        10,
        11
      ],
      "bbox2d": [
        [
          0,
          319,
          640,
          161
        ],
        [
          0,
          249,
          455,
          231
        ],
        [
          0,
          241,
          277,
          239
        ],
        [
          0,
          286,
          125,
          194
        ],
        [
          537,
          300,
          103,
          180
        ],
        [
          377,
          249,
          263,
          231
        ],
        [
          201,
          254,
          439,
          226
        ]
      ]
    },
    "940": {
      "name": "light",
      "visible_pos": [],
      "bbox2d": []
    },
    "941": {
      "name": "rack",
      "visible_pos": [
        12,
        21,
        22,
        23,
        24,
        33,
        34,
        35
      ],
      "bbox2d": [
        [
          0,
          58,
          119,
          51
        ],
        [
          549,
          106,
          91,
          59
        ],
        [
          312,
          58,
          291,
          117
        ],
        [
          69,
          88,
          282,
          79
        ],
        [
          0,
          287,
          130,
          46
        ],
        [
          555,
          325,
          85,
          64
        ],
        [
          311,
          287,
          274,
          114
        ],
        [
          63,
          312,
          287,
          79
        ]
      ]
    },
    "942": {
      "name": "towel",
      "visible_pos": [
        9,
        10,
        11,
        21,
        22,
        23,
        33,
        34,
        35
      ],
      "bbox2d": [
        [
          633,
          30,
          7,
          30
        ],
        [
          355,
          0,
          41,
          63
        ],
        [
          90,
          0,
          53,
          67
        ],
        [
          604,
          118,
          36,
          182
        ],
        [
          351,
          142,
          43,
          148
        ],
        [
          120,
          134,
          50,
          158
        ],
        [
          619,
          340,
          21,
          100
        ],
        [
          357,
          364,
          44,
          116
        ],
        [
          90,
          357,
          70,
          123
        ]
      ]
    }
  }
}