{
  "5eedd74c2a86462dafb8031559666b15": {
    "7": {
      "name": "picture",
      "visible_pos": [],
      "bbox2d": []
    },
    "9": {
      "name": "picture",
      "visible_pos": [],
      "bbox2d": []
    },
    "14": {
      "name": "picture",
      "visible_pos": [],
      "bbox2d": []
    },
    "16": {
      "name": "picture",
      "visible_pos": [],
      "bbox2d": []
    },
    "30": {
      "name": "picture",
      "visible_pos": [],
      "bbox2d": []
    },
    "31": {
      "name": "picture",
      "visible_pos": [],
      "bbox2d": []
    },
    "35": {
      "name": "picture",
      "visible_pos": [],
      "bbox2d": []
    },
    "50": {
      "name": "picture",
      "visible_pos": [],
      "bbox2d": []
    },
    "54": {
      "name": "picture",
      "visible_pos": [],
      "bbox2d": []
    },
    "57": {
      "name": "picture",
      "visible_pos": [],
      "bbox2d": []
    },
    "76": {
      "name": "picture",
      "visible_pos": [],
      "bbox2d": []
    },
    "78": {
      "name": "picture",
      "visible_pos": [],
      "bbox2d": []
    },
    "84": {
      "name": "picture",
      "visible_pos": [],
      "bbox2d": []
    },
    "115": {
      "name": "picture",
      "visible_pos": [],
      "bbox2d": []
    },
    "122": {
      "name": "picture",
      "visible_pos": [],
      "bbox2d": []
    }
  }
}