{
  "ffe267c96372462682c6b01fca2732d7": {
    "711": {
      "name": "chair",
      "visible_pos": [
        5,
        6,
        7,
        8,
        18,
        19
      ],
      "bbox2d": [
        [
          612,
          214,
          28,
          266
        ],
        [
          393,
          149,
          162,
          233
        ],
        [
          179,
          152,
          185,
          217
        ],
        [
          0,
          229,
          187,
          197
        ],
        [
          397,
          372,
          79,
          108
        ],
        [
          173,
          376,
          78,
          104
        ]
      ]
    },
    "714": {
      "name": "chair",
      "visible_pos": [
        7,
        8,
        9,
        10,
        11,
        21,
        22,
        23
      ],
      "bbox2d": [
        [
          564,
          396,
          76,
          84
        ],
        [
          396,
          253,
          244,
          227
        ],
        [
          237,
          152,
          252,
          264
        ],
        [
          47,
          151,
          238,
          329
        ],
        [
          0,
          199,
          98,
          281
        ],
        [
          355,
          375,
          155,
          105
        ],
        [
          176,
          374,
          104,
          106
        ],
        [
          0,
          452,
          24,
          28
        ]
      ]
    },
    "727": {
      "name": "chair",
      "visible_pos": [
        6,
        7,
        8,
        9,
        18,
        19
      ],
      "bbox2d": [
        [
          446,
          227,
          194,
          253
        ],
        [
          253,
          215,
          242,
          265
        ],
        [
          29,
          252,
          314,
          228
        ],
        [
          0,
          404,
          203,
          76
        ],
        [
          468,
          462,
          50,
          18
        ],
        [
          244,
          447,
          66,
          33
        ]
      ]
    },
    "737": {
      "name": "chair#bottom",
      "visible_pos": [
        6,
        7,
        8,
        9,
        10
      ],
      "bbox2d": [
        [
          430,
          455,
          16,
          25
        ],
        [
          294,
          432,
          290,
          48
        ],
        [
          152,
          366,
          280,
          114
        ],
        [
          182,
          365,
          121,
          115
        ],
        [
          54,
          437,
          80,
          43
        ]
      ]
    }
  }
}