{
  "ae5f403f3b974edb8a2705f141c101ca": {
    "611": {
      "name": "ceiling#lamp",
      "visible_pos": [
        0,
        1,
        2,
        12,
        13,
        14,
        25,
        26
      ],
      "bbox2d": [
        [
          619,
          29,
          21,
          21
        ],
        [
          345,
          0,
          115,
          45
        ],
        [
          87,
          0,
          124,
          47
        ],
        [
          591,
          244,
          49,
          36
        ],
        [
          342,
          211,
          103,
          65
        ],
        [
          109,
          210,
          113,
          67
        ],
        [
          388,
          443,
          36,
          37
        ],
        [
          127,
          441,
          40,
          39
        ]
      ]
    },
    "630": {
      "name": "stool",
      "visible_pos": [
        0,
        9,
        10,
        11
      ],
      "bbox2d": [
        [
          0,
          431,
          100,
          49
        ],
        [
          429,
          391,
          156,
          89
        ],
        [
          274,
          335,
          134,
          145
        ],
        [
          108,
          344,
          160,
          136
        ]
      ]
    },
    "644": {
      "name": "table",
      "visible_pos": [
        0,
        8,
        9,
        10,
        11,
        21,
        22,
        23
      ],
      "bbox2d": [
        [
          0,
          306,
          66,
          133
        ],
        [
          603,
          418,
          37,
          62
        ],
        [
          422,
          206,
          218,
          190
        ],
        [
          252,
          194,
          203,
          186
        ],
        [
          20,
          211,
          249,
          229
        ],
        [
          468,
          435,
          153,
          45
        ],
        [
          244,
          422,
          175,
          58
        ],
        [
          0,
          443,
          179,
          37
        ]
      ]
    },
    "669": {
      "name": "vent",
      "visible_pos": [
        12,
        23,
        24,
        34,
        35
      ],
      "bbox2d": [
        [
          147,
          0,
          70,
          42
        ],
        [
          360,
          0,
          80,
          47
        ],
        [
          158,
          222,
          69,
          51
        ],
        [
          562,
          182,
          78,
          50
        ],
        [
          353,
          232,
          76,
          45
        ]
      ]
    },
    "671": {
      "name": "light#switch",
      "visible_pos": [
        6,
        7,
        18,
        19
      ],
      "bbox2d": [
        [
          452,
          141,
          12,
          24
        ],
        [
          232,
          139,
          17,
          20
        ],
        [
          454,
          365,
          17,
          25
        ],
        [
          231,
          362,
          15,
          21
        ]
      ]
    }
  }
}