{
  "d7fd6e3ab372450b8f38600aea06b680": {
    "523": {
      "name": "pot",
      "visible_pos": [
        0,
        1,
        2,
        3,
        4
      ],
      "bbox2d": [
        [
          527,
          363,
          113,
          117
        ],
        [
          369,
          296,
          188,
          183
        ],
        [
          202,
          283,
          173,
          173
        ],
        [
          0,
          314,
          213,
          166
        ],
        [
          0,
          433,
          26,
          47
        ]
      ]
    }
  }
}