{
  "e6076af6f5214c9c91e81d468e644ca5": {
    "322": {
      "name": "window",
      "visible_pos": [
        2,
        3,
        4,
        5,
        14,
        15,
        16,
        17,
        26,
        27,
        28,
        29
      ],
      "bbox2d": [
        [
          529,
          52,
          111,
          158
        ],
        [
          310,
          0,
          330,
          205
        ],
        [
          57,
          0,
          343,
          200
        ],
        [
          0,
          0,
          177,
          181
        ],
        [
          541,
          0,
          99,
          435
        ],
        [
          306,
          0,
          334,
          432
        ],
        [
          63,
          0,
          345,
          429
        ],
        [
          0,
          0,
          184,
          407
        ],
        [
          509,
          185,
          131,
          208
        ],
        [
          307,
          235,
          333,
          245
        ],
        [
          83,
          212,
          328,
          268
        ],
        [
          0,
          186,
          175,
          294
        ]
      ]
    },
    "327": {
      "name": "chair",
      "visible_pos": [
        4,
        5,
        6,
        7,
        16,
        17,
        18
      ],
      "bbox2d": [
        [
          466,
          92,
          174,
          355
        ],
        [
          257,
          79,
          210,
          298
        ],
        [
          0,
          89,
          260,
          291
        ],
        [
          0,
          216,
          66,
          250
        ],
        [
          484,
          316,
          156,
          164
        ],
        [
          258,
          305,
          222,
          175
        ],
        [
          0,
          314,
          254,
          166
        ]
      ]
    },
    "328": {
      "name": "trinkets",
      "visible_pos": [
        5,
        6,
        7,
        8,
        17,
        18,
        19
      ],
      "bbox2d": [
        [
          500,
          133,
          140,
          208
        ],
        [
          282,
          121,
          146,
          159
        ],
        [
          39,
          141,
          198,
          141
        ],
        [
          0,
          296,
          15,
          54
        ],
        [
          510,
          356,
          48,
          51
        ],
        [
          280,
          344,
          157,
          136
        ],
        [
          24,
          363,
          195,
          117
        ]
      ]
    },
    "331": {
      "name": "table",
      "visible_pos": [
        4,
        5,
        6,
        7,
        8,
        17,
        18,
        19
      ],
      "bbox2d": [
        [
          580,
          356,
          60,
          124
        ],
        [
          375,
          160,
          265,
          320
        ],
        [
          228,
          140,
          223,
          340
        ],
        [
          25,
          152,
          272,
          328
        ],
        [
          0,
          309,
          98,
          171
        ],
        [
          470,
          384,
          170,
          96
        ],
        [
          243,
          362,
          192,
          118
        ],
        [
          0,
          376,
          212,
          104
        ]
      ]
    },
    "332": {
      "name": "table",
      "visible_pos": [
        2,
        3,
        4,
        5,
        6,
        14,
        15,
        16,
        17
      ],
      "bbox2d": [
        [
          528,
          218,
          112,
          262
        ],
        [
          359,
          147,
          281,
          272
        ],
        [
          150,
          136,
          267,
          282
        ],
        [
          0,
          159,
          230,
          321
        ],
        [
          0,
          336,
          38,
          137
        ],
        [
          619,
          451,
          21,
          29
        ],
        [
          362,
          370,
          278,
          110
        ],
        [
          133,
          359,
          294,
          121
        ],
        [
          0,
          383,
          205,
          97
        ]
      ]
    },
    "335": {
      "name": "chair",
      "visible_pos": [
        0,
        1,
        2,
        11
      ],
      "bbox2d": [
        [
          321,
          397,
          158,
          83
        ],
        [
          182,
          372,
          180,
          108
        ],
        [
          121,
          413,
          89,
          67
        ],
        [
          461,
          469,
          36,
          11
        ]
      ]
    },
    "336": {
      "name": "firewood",
      "visible_pos": [
        6,
        7,
        8,
        9
      ],
      "bbox2d": [
        [
          544,
          282,
          96,
          140
        ],
        [
          352,
          239,
          94,
          103
        ],
        [
          165,
          245,
          99,
          92
        ],
        [
          0,
          316,
          71,
          89
        ]
      ]
    }
  }
}