{
  "f93e3269c709423c9e0b43ec87cb6a9a": {
    "159": {
      "name": "cabinet",
      "visible_pos": [
        0,
        8,
        9,
        10,
        11,
        12,
        21,
        22,
        23,
        24,
        25,
        26,
        27,
        28,
        33,
        34,
        35
      ],
      "bbox2d": [
        [
          0,
          0,
          169,
          460
        ],
        [
          462,
          262,
          178,
          218
        ],
        [
          309,
          231,
          331,
          189
        ],
        [
          122,
          0,
          518,
          447
        ],
        [
          0,
          0,
          377,
          480
        ],
        [
          0,
          0,
          147,
          480
        ],
        [
          322,
          468,
          310,
          12
        ],
        [
          165,
          0,
          469,
          480
        ],
        [
          73,
          0,
          302,
          480
        ],
        [
          0,
          101,
          160,
          379
        ],
        [
          639,
          97,
          1,
          1
        ],
        [
          425,
          152,
          65,
          32
        ],
        [
          247,
          171,
          63,
          21
        ],
        [
          45,
          112,
          82,
          35
        ],
        [
          598,
          116,
          42,
          32
        ],
        [
          392,
          179,
          248,
          301
        ],
        [
          179,
          176,
          197,
          304
        ]
      ]
    },
    "173": {
      "name": "chair",
      "visible_pos": [
        5,
        6,
        7,
        8,
        9,
        18,
        19,
        20
      ],
      "bbox2d": [
        [
          516,
          254,
          124,
          226
        ],
        [
          361,
          176,
          235,
          304
        ],
        [
          182,
          165,
          275,
          315
        ],
        [
          0,
          193,
          314,
          287
        ],
        [
          0,
          440,
          173,
          40
        ],
        [
          393,
          402,
          218,
          78
        ],
        [
          168,
          389,
          196,
          91
        ],
        [
          0,
          422,
          132,
          58
        ]
      ]
    },
    "185": {
      "name": "chair",
      "visible_pos": [
        0,
        1,
        2,
        11,
        12,
        13,
        23
      ],
      "bbox2d": [
        [
          316,
          124,
          103,
          251
        ],
        [
          82,
          140,
          177,
          250
        ],
        [
          0,
          415,
          84,
          59
        ],
        [
          490,
          141,
          116,
          317
        ],
        [
          316,
          347,
          34,
          133
        ],
        [
          74,
          363,
          36,
          117
        ],
        [
          554,
          364,
          39,
          116
        ]
      ]
    },
    "186": {
      "name": "light",
      "visible_pos": [
        12,
        13,
        14,
        24,
        25,
        26
      ],
      "bbox2d": [
        [
          415,
          0,
          151,
          54
        ],
        [
          192,
          0,
          136,
          68
        ],
        [
          9,
          0,
          80,
          31
        ],
        [
          406,
          196,
          129,
          87
        ],
        [
          204,
          207,
          123,
          88
        ],
        [
          0,
          154,
          122,
          110
        ]
      ]
    },
    "192": {
      "name": "chair",
      "visible_pos": [
        0,
        1,
        2,
        3,
        11,
        13,
        14,
        15
      ],
      "bbox2d": [
        [
          410,
          286,
          230,
          194
        ],
        [
          248,
          205,
          238,
          275
        ],
        [
          63,
          194,
          224,
          286
        ],
        [
          0,
          228,
          133,
          252
        ],
        [
          592,
          429,
          48,
          51
        ],
        [
          394,
          436,
          111,
          44
        ],
        [
          185,
          422,
          92,
          58
        ],
        [
          0,
          465,
          19,
          15
        ]
      ]
    },
    "193": {
      "name": "table#light",
      "visible_pos": [
        0,
        1,
        2,
        12,
        13,
        14
      ],
      "bbox2d": [
        [
          441,
          105,
          128,
          131
        ],
        [
          226,
          96,
          108,
          125
        ],
        [
          0,
          112,
          128,
          152
        ],
        [
          448,
          328,
          135,
          146
        ],
        [
          225,
          320,
          111,
          136
        ],
        [
          0,
          336,
          102,
          144
        ]
      ]
    },
    "149": {
      "name": "shelf",
      "visible_pos": [],
      "bbox2d": []
    },
    "151": {
      "name": "shelf",
      "visible_pos": [],
      "bbox2d": []
    },
    "160": {
      "name": "cabinet",
      "visible_pos": [],
      "bbox2d": []
    }
  }
}