{
  "3f189a0fa9d340ca90b22ee64d2aff5c": {
    "382": {
      "name": "tv",
      "visible_pos": [
        0,
        1,
        2,
        12,
        13,
        14
      ],
      "bbox2d": [
        [
          481,
          77,
          122,
          115
        ],
        [
          258,
          71,
          86,
          103
        ],
        [
          0,
          86,
          122,
          113
        ],
        [
          484,
          302,
          109,
          118
        ],
        [
          258,
          298,
          86,
          102
        ],
        [
          0,
          311,
          111,
          118
        ]
      ]
    },
    "388": {
      "name": "sofa#chair",
      "visible_pos": [
        7,
        8,
        9,
        10,
        11,
        19,
        20,
        21,
        22
      ],
      "bbox2d": [
        [
          478,
          226,
          162,
          254
        ],
        [
          310,
          195,
          330,
          285
        ],
        [
          108,
          204,
          413,
          260
        ],
        [
          0,
          219,
          324,
          261
        ],
        [
          0,
          258,
          132,
          222
        ],
        [
          559,
          462,
          81,
          18
        ],
        [
          315,
          424,
          139,
          56
        ],
        [
          79,
          434,
          431,
          46
        ],
        [
          196,
          452,
          121,
          28
        ]
      ]
    },
    "415": {
      "name": "art",
      "visible_pos": [
        0,
        1,
        2,
        12,
        13,
        14,
        24,
        25,
        26
      ],
      "bbox2d": [
        [
          603,
          0,
          37,
          94
        ],
        [
          336,
          0,
          33,
          78
        ],
        [
          63,
          0,
          46,
          88
        ],
        [
          567,
          65,
          64,
          253
        ],
        [
          325,
          96,
          44,
          209
        ],
        [
          87,
          81,
          55,
          231
        ],
        [
          568,
          293,
          72,
          187
        ],
        [
          326,
          320,
          46,
          160
        ],
        [
          63,
          306,
          74,
          174
        ]
      ]
    },
    "417": {
      "name": "art",
      "visible_pos": [
        0,
        1,
        2,
        12,
        13,
        14
      ],
      "bbox2d": [
        [
          417,
          158,
          85,
          137
        ],
        [
          222,
          153,
          84,
          131
        ],
        [
          0,
          184,
          106,
          157
        ],
        [
          437,
          382,
          76,
          98
        ],
        [
          215,
          377,
          86,
          103
        ],
        [
          0,
          411,
          26,
          69
        ]
      ]
    },
    "419": {
      "name": "decoration",
      "visible_pos": [
        6,
        7,
        8,
        9
      ],
      "bbox2d": [
        [
          506,
          412,
          27,
          68
        ],
        [
          340,
          361,
          83,
          119
        ],
        [
          197,
          377,
          105,
          103
        ],
        [
          1,
          475,
          19,
          5
        ]
      ]
    },
    "383": {
      "name": "curtain",
      "visible_pos": [],
      "bbox2d": []
    }
  }
}