{
  "fbce2bf4588444e492e9a9e66fadb5fa": {
    "285": {
      "name": "table#lamp",
      "visible_pos": [
        8,
        9,
        10,
        20,
        21,
        22
      ],
      "bbox2d": [
        [
          415,
          143,
          169,
          208
        ],
        [
          220,
          133,
          146,
          192
        ],
        [
          0,
          152,
          168,
          218
        ],
        [
          429,
          366,
          193,
          114
        ],
        [
          206,
          356,
          166,
          124
        ],
        [
          0,
          375,
          145,
          105
        ]
      ]
    },
    "308": {
      "name": "end#table",
      "visible_pos": [
        7,
        8,
        9,
        10
      ],
      "bbox2d": [
        [
          558,
          403,
          82,
          77
        ],
        [
          392,
          314,
          142,
          155
        ],
        [
          238,
          292,
          119,
          129
        ],
        [
          50,
          315,
          157,
          165
        ]
      ]
    },
    "320": {
      "name": "plant",
      "visible_pos": [
        0,
        9,
        10,
        11
      ],
      "bbox2d": [
        [
          0,
          346,
          87,
          134
        ],
        [
          498,
          323,
          142,
          146
        ],
        [
          323,
          287,
          119,
          108
        ],
        [
          144,
          288,
          126,
          121
        ]
      ]
    },
    "291": {
      "name": "plant",
      "visible_pos": [],
      "bbox2d": []
    },
    "304": {
      "name": "pillar",
      "visible_pos": [],
      "bbox2d": []
    }
  }
}