{
  "6a99c723d40b429e96a29c8ce7532d1d": {
    "593": {
      "name": "picture",
      "visible_pos": [
        4,
        5,
        6,
        16,
        17,
        18,
        28,
        29,
        30
      ],
      "bbox2d": [
        [
          497,
          0,
          143,
          164
        ],
        [
          260,
          0,
          119,
          138
        ],
        [
          0,
          0,
          140,
          149
        ],
        [
          494,
          187,
          139,
          202
        ],
        [
          267,
          196,
          104,
          165
        ],
        [
          4,
          191,
          139,
          181
        ],
        [
          513,
          414,
          127,
          66
        ],
        [
          259,
          425,
          119,
          55
        ],
        [
          0,
          419,
          126,
          61
        ]
      ]
    }
  }
}