{
  "8b66d02c268548649cc0cc3c8a1440f9": {
    "243": {
      "name": "cabinet",
      "visible_pos": [
        4,
        5,
        6,
        7,
        8,
        17,
        18,
        19
      ],
      "bbox2d": [
        [
          467,
          253,
          173,
          227
        ],
        [
          321,
          176,
          307,
          304
        ],
        [
          138,
          170,
          274,
          310
        ],
        [
          0,
          208,
          245,
          272
        ],
        [
          0,
          341,
          71,
          139
        ],
        [
          359,
          402,
          205,
          78
        ],
        [
          173,
          395,
          194,
          85
        ],
        [
          0,
          444,
          91,
          36
        ]
      ]
    },
    "244": {
      "name": "chair",
      "visible_pos": [
        3,
        4,
        5,
        6
      ],
      "bbox2d": [
        [
          437,
          387,
          168,
          93
        ],
        [
          299,
          331,
          151,
          149
        ],
        [
          168,
          339,
          133,
          141
        ],
        [
          0,
          421,
          148,
          59
        ]
      ]
    }
  }
}