{
  "69b8eb3000854ba48b2882a35f125af5": {
    "293": {
      "name": "mirror",
      "visible_pos": [
        0,
        1,
        2,
        11,
        12,
        13,
        14,
        23,
        24,
        25,
        26,
        35
      ],
      "bbox2d": [
        [
          310,
          0,
          330,
          144
        ],
        [
          38,
          0,
          350,
          159
        ],
        [
          0,
          0,
          146,
          165
        ],
        [
          560,
          0,
          80,
          173
        ],
        [
          312,
          0,
          328,
          367
        ],
        [
          68,
          0,
          312,
          383
        ],
        [
          0,
          0,
          154,
          386
        ],
        [
          549,
          0,
          91,
          395
        ],
        [
          315,
          142,
          325,
          338
        ],
        [
          52,
          114,
          350,
          366
        ],
        [
          0,
          54,
          217,
          426
        ],
        [
          486,
          65,
          154,
          415
        ]
      ]
    },
    "313": {
      "name": "chair",
      "visible_pos": [
        3,
        4,
        5,
        6,
        15,
        16,
        17
      ],
      "bbox2d": [
        [
          533,
          201,
          107,
          279
        ],
        [
          345,
          165,
          146,
          236
        ],
        [
          144,
          172,
          169,
          227
        ],
        [
          0,
          280,
          138,
          193
        ],
        [
          607,
          451,
          33,
          29
        ],
        [
          349,
          389,
          97,
          91
        ],
        [
          118,
          397,
          105,
          83
        ]
      ]
    },
    "301": {
      "name": "decoration",
      "visible_pos": [],
      "bbox2d": []
    }
  }
}