{
  "b33f3e2cf71b47c0b32bfdc286123cd3": {
    "79": {
      "name": "plant",
      "visible_pos": [
        0,
        1,
        9,
        10,
        11,
        12,
        23
      ],
      "bbox2d": [
        [
          31,
          189,
          309,
          291
        ],
        [
          0,
          248,
          202,
          232
        ],
        [
          605,
          375,
          35,
          105
        ],
        [
          410,
          237,
          230,
          243
        ],
        [
          242,
          186,
          292,
          294
        ],
        [
          133,
          417,
          199,
          63
        ],
        [
          320,
          413,
          193,
          67
        ]
      ]
    },
    "95": {
      "name": "box",
      "visible_pos": [
        8,
        9,
        10,
        11,
        21,
        22,
        23
      ],
      "bbox2d": [
        [
          635,
          353,
          5,
          26
        ],
        [
          419,
          165,
          117,
          155
        ],
        [
          230,
          156,
          101,
          147
        ],
        [
          0,
          188,
          139,
          170
        ],
        [
          441,
          389,
          127,
          91
        ],
        [
          218,
          380,
          114,
          100
        ],
        [
          0,
          415,
          90,
          65
        ]
      ]
    },
    "106": {
      "name": "end#table",
      "visible_pos": [
        8,
        9,
        10,
        11
      ],
      "bbox2d": [
        [
          543,
          317,
          97,
          163
        ],
        [
          364,
          268,
          191,
          165
        ],
        [
          181,
          246,
          185,
          192
        ],
        [
          0,
          269,
          206,
          211
        ]
      ]
    }
  }
}