{
  "76c2cb3b13ec4a52ac5edca0fd2aad40": {
    "951": {
      "name": "fence",
      "visible_pos": [
        0,
        1,
        2,
        3,
        4,
        5,
        6,
        12,
        13,
        14,
        15,
        16,
        17,
        18,
        24,
        25,
        26,
        27,
        28,
        29,
        30
      ],
      "bbox2d": [
        [
          421,
          0,
          219,
          342
        ],
        [
          187,
          0,
          453,
          441
        ],
        [
          0,
          0,
          640,
          435
        ],
        [
          0,
          0,
          640,
          351
        ],
        [
          0,
          0,
          640,
          423
        ],
        [
          0,
          0,
          491,
          452
        ],
        [
          0,
          0,
          250,
          367
        ],
        [
          417,
          197,
          223,
          283
        ],
        [
          194,
          174,
          446,
          306
        ],
        [
          0,
          169,
          640,
          311
        ],
        [
          0,
          179,
          640,
          301
        ],
        [
          0,
          169,
          640,
          311
        ],
        [
          0,
          175,
          479,
          305
        ],
        [
          0,
          196,
          253,
          284
        ],
        [
          442,
          430,
          198,
          50
        ],
        [
          187,
          402,
          453,
          78
        ],
        [
          0,
          394,
          640,
          86
        ],
        [
          0,
          407,
          640,
          73
        ],
        [
          0,
          395,
          640,
          85
        ],
        [
          0,
          403,
          490,
          77
        ],
        [
          0,
          430,
          231,
          50
        ]
      ]
    }
  }
}